xrpert/__init__.py
xrpert-0.0.1.dist-info/WHEEL
xrpert-0.0.1.dist-info/METADATA
xrpert-0.0.1.dist-info/RECORD
