Metadata-Version: 2.3
Name: xrpert
Version: 0.0.1
Summary: xrpert
Keywords: python
Author: Jiacheng Wang
Author-email: Jiacheng Wang <jcwang.dev@gmail.com>
License: MIT
Classifier: Development Status :: 1 - Planning
Classifier: Intended Audience :: Science/Research
Classifier: Operating System :: OS Independent
Classifier: Programming Language :: Python :: 3 :: Only
Classifier: Programming Language :: Python :: 3.11
Classifier: Programming Language :: Python :: 3.12
Requires-Dist: matplotlib
Requires-Dist: pytest>=8.3 ; extra == 'dev'
Requires-Dist: pytest-cov>=6 ; extra == 'dev'
Maintainer: Jiacheng Wang
Maintainer-email: Jiacheng Wang <jcwang.dev@gmail.com>
Requires-Python: >=3.11, <3.13
Provides-Extra: dev
